a2a_line_client/__init__.py
a2a_line_client/file.py
a2a_line_client/handler.py
a2a_line_client/parser.py
a2a_line_client/renderer.py
a2a_line_client/sender.py
a2a_line_client/server.py
a2a_line_client/user_state.py
a2a_line_client/worker.py
a2a_line_client-0.1.0.dist-info/METADATA
a2a_line_client-0.1.0.dist-info/WHEEL
a2a_line_client-0.1.0.dist-info/licenses/LICENSE
a2a_line_client-0.1.0.dist-info/RECORD
