Metadata-Version: 2.4
Name: a2a-line-client
Version: 0.1.0
Summary: A LINE Bot client built with FastAPI and A2A SDK
Project-URL: Homepage, https://github.com/ryukez/a2a-line-client
Project-URL: Repository, https://github.com/ryukez/a2a-line-client
Project-URL: Issues, https://github.com/ryukez/a2a-line-client/issues
Author-email: Ryunosuke Iwai <ryunosuke.iwai@gmail.com>
License: MIT
License-File: LICENSE
Keywords: a2a,bot,fastapi,line,messaging
Classifier: Development Status :: 3 - Alpha
Classifier: Intended Audience :: Developers
Classifier: License :: OSI Approved :: MIT License
Classifier: Programming Language :: Python :: 3
Classifier: Programming Language :: Python :: 3.13
Classifier: Topic :: Communications :: Chat
Classifier: Topic :: Software Development :: Libraries :: Python Modules
Requires-Python: >=3.13
Requires-Dist: a2a-sdk>=0.2.8
Requires-Dist: fastapi>=0.115.12
Requires-Dist: line-bot-sdk>=3.17.1
Requires-Dist: python-dotenv>=1.1.0
Requires-Dist: uvicorn>=0.34.3
Provides-Extra: dev
Requires-Dist: black>=22.0.0; extra == 'dev'
Requires-Dist: flake8>=4.0.0; extra == 'dev'
Requires-Dist: mypy>=0.900; extra == 'dev'
Requires-Dist: pytest>=7.0.0; extra == 'dev'
